CHANGES.rst
MANIFEST.in
README.rst
TODO.rst
setup.py
invisibleroads_scaffolds/__init__.py
invisibleroads_scaffolds.egg-info/PKG-INFO
invisibleroads_scaffolds.egg-info/SOURCES.txt
invisibleroads_scaffolds.egg-info/dependency_links.txt
invisibleroads_scaffolds.egg-info/entry_points.txt
invisibleroads_scaffolds.egg-info/not-zip-safe
invisibleroads_scaffolds.egg-info/requires.txt
invisibleroads_scaffolds.egg-info/top_level.txt