Metadata-Version: 1.0
Name: invisibleroads-scaffolds
Version: 1.8.0
Summary: Pyramid application scaffolds based on invisibleroads.com
Home-page: https://github.com/invisibleroads/invisibleroads-scaffolds
Author: Roy Hyunjin Han
Author-email: starsareblueandfaraway@gmail.com
License: MIT
Keywords: web wsgi bfg pylons pyramid
Platform: UNKNOWN
Classifier: Intended Audience :: Developers
Classifier: Framework :: Pylons
Classifier: Programming Language :: Python
Classifier: License :: OSI Approved :: MIT License
